django_auto_model_loader/__init__.py
django_auto_model_loader/aliases.py
django_auto_model_loader/apps.py
django_auto_model_loader/decorators.py
django_auto_model_loader/middleware.py
django_auto_model_loader-1.0.1.dist-info/licenses/LICENSE
django_auto_model_loader-1.0.1.dist-info/METADATA
django_auto_model_loader-1.0.1.dist-info/WHEEL
django_auto_model_loader-1.0.1.dist-info/top_level.txt
django_auto_model_loader-1.0.1.dist-info/RECORD
