Metadata-Version: 2.4
Name: django-auto-model-loader
Version: 1.0.1
Summary: Middleware for auto-loading Django models from URL parameters
Home-page: https://github.com/Volbeck/django_auto_model_loader
Author: Dennis Tverdostup
Author-email: Dennis Tverdostup <denystverdostup@gmail.com>
License: MIT
Project-URL: Repository, https://github.com/Volbeck/django_auto_model_loader
Project-URL: Issues, https://github.com/Volbeck/django_auto_model_loader/issues
Keywords: django,autoload,models,model
Classifier: Framework :: Django
Classifier: Programming Language :: Python :: 3
Classifier: License :: OSI Approved :: MIT License
Classifier: Operating System :: OS Independent
Requires-Python: >=2.7
License-File: LICENSE
Requires-Dist: Django>=1.8
Requires-Dist: inflection>=0.5.1
Dynamic: author
Dynamic: home-page
Dynamic: license-file
Dynamic: requires-python
